dosdp/__init__.py
dosdp/__main__.py
dosdp/validator.py
dosdp/document/__init__.py
dosdp/document/document.py
dosdp/document/pattern/__init__.py
dosdp/document/pattern/patterns_create_docs.py
dosdp/document/pattern/patterns_create_overview.py
dosdp/document/schema/__init__.py
dosdp/document/schema/schema_create_docs.py
schema/__init__.py
schema/dosdp_schema.md
schema/dosdp_schema.yaml
schema/dosdp_schema_doc.ini
schema/schema_validator.py
dosdp-0.1.10.dev1.dist-info/METADATA
dosdp-0.1.10.dev1.dist-info/WHEEL
dosdp-0.1.10.dev1.dist-info/entry_points.txt
dosdp-0.1.10.dev1.dist-info/top_level.txt
dosdp-0.1.10.dev1.dist-info/RECORD
