Metadata-Version: 2.1
Name: dosdp
Version: 0.1.10.dev1
Summary: The aim of this project is to specify a simple OWL design pattern system that can easily be consumed, whatever your code base.
Home-page: https://github.com/INCATools/dead_simple_owl_design_patterns
Author: INCATools
License: GPL-3.0 License
Platform: UNKNOWN
Classifier: Programming Language :: Python :: 3
Classifier: License :: OSI Approved :: GNU General Public License v3 (GPLv3)
Classifier: Operating System :: OS Independent
Requires-Dist: PyYAML
Requires-Dist: jsonschema
Requires-Dist: requests
Requires-Dist: jsonpath-rw
Requires-Dist: ruamel.yaml
Requires-Dist: jsonschema2md
Requires-Dist: pandas
